obsidian_linker/__init__.py
obsidian_linker/main.py
obsidian_linker-0.1.2.dist-info/METADATA
obsidian_linker-0.1.2.dist-info/WHEEL
obsidian_linker-0.1.2.dist-info/entry_points.txt
obsidian_linker-0.1.2.dist-info/RECORD
