Metadata-Version: 2.1
Name: obsidian-linker
Version: 0.1.2
Summary: 
Author: CO
Author-email: o@simor.group
Requires-Python: >=3.10,<4.0
Classifier: Programming Language :: Python :: 3
Classifier: Programming Language :: Python :: 3.10
Classifier: Programming Language :: Python :: 3.11
Requires-Dist: click (>=8.1.7,<9.0.0)
Requires-Dist: openai (>=1.3.9,<2.0.0)
Requires-Dist: python-dotenv (>=1.0.0,<2.0.0)
